DirecTracer/__init__.py
DirecTracer/src/DirectTracer.py
DirecTracer/src/__init__.py
DirecTracer/test/__init__.py
DirecTracer/test/generate_sample_structure.py
DirecTracer/test/test_DirecTracer.py
DirecTracer-1.0.7.dist-info/LICENSE.txt
DirecTracer-1.0.7.dist-info/METADATA
DirecTracer-1.0.7.dist-info/WHEEL
DirecTracer-1.0.7.dist-info/top_level.txt
DirecTracer-1.0.7.dist-info/RECORD
