Metadata-Version: 2.1
Name: DirecTracer
Version: 1.0.7
Summary: DirecTracer is a Python script that generates a directory structure in both text and Markdown formats. It can be used to visualize the hierarchy of folders and files in a given directory, while also excluding specific folders and file extensions.
Home-page: https://github.com/Hardvan/DirecTracer
Author: Hardik Pawar
Author-email: hardikpawarh@gmail.com
License: UNKNOWN
Keywords: directory structure,visualization,folder hierarchy,file organization
Platform: UNKNOWN
Classifier: Programming Language :: Python :: 3
Classifier: License :: OSI Approved :: MIT License
Classifier: Operating System :: OS Independent
Requires-Python: >=3.6
License-File: LICENSE.txt
